<proof>
  <step>
    <number>1</number>
    <sentence>p</sentence>
    <justification>Premise</justification>
  </step>
  <step>
    <number>2</number>
    <sentence>~(p & ~q)</sentence>
    <justification>Premise</justification>
  </step>
  <step>
    <number>3</number>
    <sentence>~q</sentence>
    <justification>Assumption</justification>
  </step>
  <step>
    <number>4</number>
    <sentence>p</sentence>
    <justification>Reiteration</justification>
    <antecedent>1</antecedent>
  </step>
  <step>
    <number>5</number>
    <sentence>p & ~q</sentence>
    <justification>And Introduction</justification>
    <antecedent>4</antecedent>
    <antecedent>3</antecedent>
  </step>
  <step>
    <number>6</number>
    <sentence>~q => p & ~q</sentence>
    <justification>Implication Introduction</justification>
    <antecedent>3</antecedent>
    <antecedent>5</antecedent>
  </step>
  <step>
    <number>7</number>
    <sentence>~q</sentence>
    <justification>Assumption</justification>
  </step>
  <step>
    <number>8</number>
    <sentence>~(p & ~q)</sentence>
    <justification>Reiteration</justification>
    <antecedent>2</antecedent>
  </step>
  <step>
    <number>9</number>
    <sentence>~q => ~(p & ~q)</sentence>
    <justification>Implication Introduction</justification>
    <antecedent>7</antecedent>
    <antecedent>8</antecedent>
  </step>
  <step>
    <number>10</number>
    <sentence>~~q</sentence>
    <justification>Negation Introduction</justification>
    <antecedent>6</antecedent>
    <antecedent>9</antecedent>
  </step>
  <step>
    <number>11</number>
    <sentence>q</sentence>
    <justification>Negation Elimination</justification>
    <antecedent>10</antecedent>
  </step>
</proof>
